{"891319231436685342": {"wallet": 7342, "bank": 13, "last_interest_time": "2024-12-03T11:28:08.164503", "portfolio": {"Hazel.Inc": 103, "Codex": 124, "DataSphere": 21}, "inventory": {"valentines-box": 12, "chocolate-box": 17, "pink-rose": 114, "chocolate": 6, "love-letter": 2, "room-card": 5, "phone": 1}, "effects": {}, "badges": ["Trivia-Master", "Speedster", "Streak-King", "Task-Master"]}, "866575663271116851": {"wallet": 552, "bank": 2000, "last_interest_time": "2024-12-04T14:05:29.467637", "portfolio": {}, "inventory": {"dice": 8, "soda": 1, "pink-rose": 6, "rose": 9, "teddy-bear": 1, "love-letter": 13, "chocolate-box": 2, "valentines-box": 3}, "effects": {}}, "839182501091344444": {"wallet": 3245, "bank": 0, "last_interest_time": "2024-12-06T21:15:30.123962", "portfolio": {}, "badges": ["Speedster", "Trivia-Master"], "inventory": {"pink-rose": 1, "teddy-bear": 2, "teddy-heart": 1}}, "826765555776094258": {"wallet": 9996, "bank": 0, "last_interest_time": "2024-12-06T21:15:40.502163", "portfolio": {}, "inventory": {}, "effects": {"salary_boost": {"multiplier": 19.199999999999996, "expires_at": 1741368837.46474}}}, "767963841333035009": {"wallet": 0, "bank": 184, "last_interest_time": "2024-12-16T23:27:58.662048", "portfolio": {}}, "866580615553482773": {"wallet": 1233, "bank": 0, "last_interest_time": "2024-12-24T22:04:15.618263", "portfolio": {}, "inventory": {}}, "372280967827685376": {"wallet": 160, "bank": 0, "last_interest_time": "2024-12-26T16:55:44.708205", "portfolio": {}, "inventory": {}}, "749134968021712957": {"wallet": 142, "bank": 0, "last_interest_time": "2024-12-26T17:04:51.073136", "portfolio": {}}, "704536277579595866": {"wallet": 792, "bank": 0, "last_interest_time": "2024-12-26T18:26:45.855810", "portfolio": {}, "inventory": {"valentines-box": 1, "teddy-bear": 1, "chocolate-box": 2, "chocolate": 1, "pink-rose": 1}}, "653594236792471553": {"wallet": 140, "bank": 0, "last_interest_time": "2024-12-26T20:16:47.517798", "portfolio": {}}, "776044424005287946": {"wallet": 100, "bank": 0, "last_interest_time": "2025-01-04T11:01:20.378913", "portfolio": {}}, "1323212945370517505": {"wallet": 110, "bank": 0, "last_interest_time": "2025-01-13T09:45:31.383604", "portfolio": {}}, "1246704702108864595": {"wallet": 448, "bank": 0, "last_interest_time": "2025-01-16T11:07:11.301218", "portfolio": {}}, "704041650401312829": {"wallet": 300, "bank": 0, "last_interest_time": "2025-01-16T11:14:30.539853", "portfolio": {}}, "756558672993321050": {"wallet": 722, "bank": 0, "last_interest_time": "2025-01-16T11:17:26.872656", "portfolio": {}, "badges": ["Speedster"], "inventory": {"valentines-box": 4}}, "802611045565726762": {"wallet": 273, "bank": 0, "last_interest_time": "2025-01-16T13:24:39.490269", "portfolio": {}}, "1027623647952773162": {"wallet": 2123, "bank": 0, "last_interest_time": "2025-01-16T17:07:04.154284", "portfolio": {}, "inventory": {"pink-rose": 2}}, "773861111824515113": {"wallet": 282, "bank": 0, "last_interest_time": "2025-01-18T16:06:07.678885", "portfolio": {}}, "1131636289033228438": {"wallet": 412, "bank": 50, "last_interest_time": "2025-01-18T20:14:43.397446", "portfolio": {"Codex": 2}}, "1239888149388460045": {"wallet": 260, "bank": 0, "last_interest_time": "2025-01-18T20:15:33.215263", "portfolio": {}}, "1209341332452286475": {"wallet": 100, "bank": 0, "last_interest_time": "2025-01-19T00:59:20.897803", "portfolio": {}}, "1014139734240534548": {"wallet": 217, "bank": 0, "last_interest_time": "2025-01-19T11:57:12.903311", "portfolio": {}}, "1156798489519476807": {"wallet": 100, "bank": 0, "last_interest_time": "2025-01-22T06:33:24.448855", "portfolio": {}}, "1334154702488731684": {"wallet": 10800, "bank": 0, "last_interest_time": "2025-01-30T07:42:22.887995", "portfolio": {}, "inventory": {"phone": 1, "love-letter": 25, "teddy-bear": 16, "teddy-heart": 19, "chocolate-box": 2, "valentines-box": 7, "rose": 41}}, "878590775309500427": {"wallet": 241, "bank": 0, "last_interest_time": "2025-02-03T20:58:26.869222", "portfolio": {}}, "1042532785841254420": {"wallet": 100, "bank": 0, "last_interest_time": "2025-02-09T06:31:33.928759", "portfolio": {}}, "712559633293770753": {"wallet": 100, "bank": 0, "last_interest_time": "2025-02-09T20:52:15.170257", "portfolio": {}}, "1116329635903438858": {"wallet": 100, "bank": 0, "last_interest_time": "2025-02-10T06:42:26.610224", "portfolio": {}}, "1279715815821938732": {"wallet": 200, "bank": 0, "last_interest_time": "2025-02-10T07:19:11.510891", "portfolio": {}, "inventory": {"valentines-box": 10}}, "688334058857562143": {"wallet": 110, "bank": 225, "last_interest_time": "2025-02-10T10:36:33.701372", "portfolio": {}}, "1333796940789321769": {"wallet": 175, "bank": 0, "last_interest_time": "2025-02-10T11:12:32.649848", "portfolio": {}}, "770494792773271562": {"wallet": 152, "bank": 0, "last_interest_time": "2025-02-10T18:49:40.627111", "portfolio": {}}, "932554316995235840": {"wallet": 193, "bank": 0, "last_interest_time": "2025-02-12T04:17:24.433608", "portfolio": {}}, "705273916607692821": {"wallet": 221, "bank": 0, "last_interest_time": "2025-02-12T04:17:24.434790", "portfolio": {}}, "1053102403152531457": {"wallet": 158, "bank": 0, "last_interest_time": "2025-02-12T04:17:24.435770", "portfolio": {}}, "344519020088786945": {"wallet": 111, "bank": 0, "last_interest_time": "2025-02-14T16:19:18.105470", "portfolio": {}}, "587918732425166858": {"wallet": 114, "bank": 0, "last_interest_time": "2025-02-14T18:46:40.358692", "portfolio": {}}, "1164268313334001806": {"wallet": 762, "bank": 0, "last_interest_time": "2025-02-17T12:15:02.063513", "portfolio": {}}, "1252173630679421010": {"wallet": 275, "bank": 0, "last_interest_time": "2025-02-17T12:16:58.100149", "portfolio": {}}, "872020990945808395": {"wallet": 219, "bank": 0, "last_interest_time": "2025-02-17T16:45:07.361812", "portfolio": {}}, "933727951642570862": {"wallet": 398, "bank": 0, "last_interest_time": "2025-02-18T08:29:19.791110", "portfolio": {}}, "984160444262518854": {"wallet": 3194, "bank": 0, "last_interest_time": "2025-02-18T19:58:49.608047", "portfolio": {}, "badges": ["Trivia-Master"]}, "578593764088479775": {"wallet": 1005, "bank": 2554, "last_interest_time": "2025-02-18T20:05:50.988647", "portfolio": {}, "badges": ["Speedster", "Trivia-Master"]}, "1005724003803090995": {"wallet": 110, "bank": 0, "last_interest_time": "2025-02-19T02:14:51.722448", "portfolio": {}}, "821267146743087124": {"wallet": 234, "bank": 0, "last_interest_time": "2025-02-19T17:09:18.489926", "portfolio": {}}, "1272198178485047336": {"wallet": 239, "bank": 0, "last_interest_time": "2025-02-19T18:20:21.212030", "portfolio": {}}, "853283237630967839": {"wallet": 370, "bank": 0, "last_interest_time": "2025-02-20T07:24:31.380674", "portfolio": {}}, "891779397277872188": {"wallet": 123, "bank": 0, "last_interest_time": "2025-02-20T15:29:42.910535", "portfolio": {}}, "1295047885494292502": {"wallet": 110, "bank": 0, "last_interest_time": "2025-02-21T09:01:00.387378", "portfolio": {}, "inventory": {"rose": 1}}, "250680262164217858": {"wallet": 291, "bank": 0, "last_interest_time": "2025-02-21T15:09:35.831762", "portfolio": {}, "inventory": {"coffee": 1}}, "1118900114329714819": {"wallet": 737, "bank": 0, "last_interest_time": "2025-02-22T12:27:13.677617", "portfolio": {}, "inventory": {"rose": 4, "pink-rose": 4}}, "745475129789644843": {"wallet": 320, "bank": 0, "last_interest_time": "2025-02-22T13:57:23.555631", "portfolio": {}}, "865542032175792172": {"wallet": 338, "bank": 0, "last_interest_time": "2025-02-22T14:54:06.288014", "portfolio": {}}, "1192523789909635174": {"wallet": 127, "bank": 0, "last_interest_time": "2025-02-22T14:54:56.882292", "portfolio": {}}, "859987412611497994": {"wallet": 100, "bank": 0, "last_interest_time": "2025-02-22T17:01:19.112432", "portfolio": {}}, "1328797746865635460": {"wallet": 137, "bank": 0, "last_interest_time": "2025-02-22T18:27:13.147182", "portfolio": {}}, "818866339929522176": {"wallet": 182, "bank": 0, "last_interest_time": "2025-02-22T20:28:45.050371", "portfolio": {}}, "704749030349078648": {"wallet": 123, "bank": 0, "last_interest_time": "2025-02-23T08:25:36.659323", "portfolio": {}}, "789469947746975744": {"wallet": 112, "bank": 0, "last_interest_time": "2025-02-24T20:44:42.778828", "portfolio": {}}, "632263082978050049": {"wallet": 100, "bank": 0, "last_interest_time": "2025-02-27T07:48:06.999494", "portfolio": {}}, "1218599663859404892": {"wallet": 100, "bank": 0, "last_interest_time": "2025-02-28T20:03:32.994864", "portfolio": {}, "inventory": {"chocolate": 1}}, "519850436899897346": {"wallet": 100, "bank": 0, "last_interest_time": "2025-03-07T20:35:48.720689", "portfolio": {}}}